dlu_core/__init__.py
dlu_core/object_detection/__init__.py
dlu_core/object_detection/example_configs.py
dlu_core/object_detection/yolo/__init__.py
dlu_core/object_detection/yolo/dataset.py
dlu_core/object_detection/yolo/utils.py
dlu_core/utils.py
dlu_core-0.1.3.dist-info/METADATA
dlu_core-0.1.3.dist-info/WHEEL
dlu_core-0.1.3.dist-info/RECORD
