Metadata-Version: 2.1
Name: dlu_core
Version: 0.1.3
Summary: My utility functions for work
Author: Danylo Kunyk
Author-email: kunyk1507@gmail.com
Requires-Python: >=3.9,<4.0
Classifier: Programming Language :: Python :: 3
Classifier: Programming Language :: Python :: 3.9
Classifier: Programming Language :: Python :: 3.10
Classifier: Programming Language :: Python :: 3.11
Requires-Dist: albumentations (>=1.3.1,<2.0.0)
Requires-Dist: black (>=23.11.0,<24.0.0)
Requires-Dist: hydra-core (>=1.3.2,<2.0.0)
Requires-Dist: isort (>=5.12.0,<6.0.0)
Requires-Dist: matplotlib (>=3.8.2,<4.0.0)
Requires-Dist: numpy (>=1.26.2,<2.0.0)
Requires-Dist: pandas (>=2.1.3,<3.0.0)
Requires-Dist: pylint (>=3.0.2,<4.0.0)
Requires-Dist: tqdm (>=4.66.1,<5.0.0)
